{
  "vong_1": {
    "chinh_sach_phap_luat_va_y_te": {
      "trac_nghiem": [
        {
          "cau_hoi_so": 1,
          "id": "CSPL_TN_1",
          "category": "Chính sách pháp luật và Y tế",
          "subcategory": "Chính sách pháp luật về ATVSLĐ",
          "type_question": "Trắc nghiệm",
          "image_id": "images/illustrative_cspl_tn_1.jpg",
          "use_image": "Yes",
          "position_image": "Right",
          "question_image": "No",
          "cau_hoi": "Anh/Chị hãy cho biết An toàn vệ sinh viên có bao nhiêu quyền lợi và nghĩa vụ?",
          "phuong_an": {
            "a": "04 quyền và 05 nghĩa vụ.",
            "b": "05 quyền và 04 nghĩa vụ.",
            "c": "03 quyền và 05 nghĩa vụ.",
            "d": "04 quyền và 06 nghĩa vụ."
          },
          "dap_an_dung": "a",
          "speech_id_question": "CSPL_TN_1.wav",
          "speech_id_options_A": "CSPL_TN_1_A.wav",
          "speech_id_options_B": "CSPL_TN_1_B.wav",
          "speech_id_options_C": "CSPL_TN_1_C.wav",
          "speech_id_options_D": "CSPL_TN_1_D.wav",
          "speech_id_answer": "CSPL_TN_1_ans.wav",
          "bg_image": "images\\bg\\bg1.jpg"
        },
        {
          "cau_hoi_so": 2,
          "id": "CSPL_TN_2",
          "category": "Chính sách pháp luật và Y tế",
          "subcategory": "Chính sách pháp luật về ATVSLĐ",
          "type_question": "Trắc nghiệm",
          "image_id": "images/illustrative_cspl_tn_2.jpg",
          "use_image": "Yes",
          "position_image": "Right",
          "question_image": "No",
          "cau_hoi": "Anh/Chị hãy cho biết nội dung hoạt động hàng ngày trước ca làm việc của mạng lưới An toàn vệ sinh viên?",
          "phuong_an": {
            "a": "Kiểm tra điều kiện môi trường làm việc.",
            "b": "Nhắc nhở người lao động trong tổ sử dụng đầy đủ phương tiện bảo vệ cá nhân.",
            "c": "Cả 2 nội dung trên."
          },
          "dap_an_dung": "c",
          "speech_id_question": "CSPL_TN_2.wav",
          "speech_id_options_A": "CSPL_TN_2_A.wav",
          "speech_id_options_B": "CSPL_TN_2_B.wav",
          "speech_id_options_C": "CSPL_TN_2_C.wav",
          "speech_id_options_D": null,
          "speech_id_answer": "CSPL_TN_2_ans.wav",
          "bg_image": "images\\bg\\bg2.jpg"
        },
        {
          "cau_hoi_so": 3,
          "id": "CSPL_TN_3",
          "category": "Chính sách pháp luật và Y tế",
          "subcategory": "Chính sách pháp luật về ATVSLĐ",
          "type_question": "Trắc nghiệm",
          "image_id": "images/illustrative_cspl_tn_3.jpg",
          "use_image": "Yes",
          "position_image": "Right",
          "question_image": "No",
          "cau_hoi": "Anh/Chị hãy cho biết hoạt động của mạng lưới an toàn vệ sinh viên nhằm?",
          "phuong_an": {
            "a": "Giúp Ban chấp hành công đoàn cơ sở thực hiện tốt công tác ATVSLĐ.",
            "b": "Giúp người sử dụng lao động thực hiện tốt công tác ATVSLĐ.",
            "c": "Đẩy mạnh phong trào \"Xanh - Sạch- Đẹp, Bảo đảm ATVSLĐ\" tại doanh nghiệp.",
            "d": "Cả 3 câu đều đúng."
          },
          "dap_an_dung": "d",
          "speech_id_question": "CSPL_TN_3.wav",
          "speech_id_options_A": "CSPL_TN_3_A.wav",
          "speech_id_options_B": "CSPL_TN_3_B.wav",
          "speech_id_options_C": "CSPL_TN_3_C.wav",
          "speech_id_options_D": "CSPL_TN_3_D.wav",
          "speech_id_answer": "CSPL_TN_3_ans.wav",
          "bg_image": "images\\bg\\bg3.jpg"
        },
        {
          "cau_hoi_so": 4,
          "id": "CSPL_TN_4",
          "category": "Chính sách pháp luật và Y tế",
          "subcategory": "Chính sách pháp luật về ATVSLĐ",
          "type_question": "Trắc nghiệm",
          "image_id": null,
          "use_image": "No",
          "position_image": "Right",
          "question_image": "No",
          "cau_hoi": "Anh/Chị hãy đánh dấu câu sai trong nội dung cấp cứu ngừng tim, ngừng thở do điện giật?",
          "phuong_an": {
            "a": "Nếu nạn nhân bất tỉnh ngừng tim, ngừng thở do điện giật thì phải được tách khỏi nguồn điện rồi mới tiến hành cấp cứu.",
            "b": "Để nạn nhân nằm ngửa trên mặt phẳng cứng, cấp cứu viên quỳ sát bên nạn nhân, đặt gót tay lên xương ức, cách mỏm ức khoảng 3cm, tay kia đè chồng lên và dùng sức của cả cơ thể ấn xuống hai tay tạo áp lực mạnh làm lún xương ức rồi thả ra. Động tác ép và thả nhanh gọn, dứt khoát.",
            "c": "Nếu chỉ có một cấp cứu viên thì cứ ép tim 15 lần trong 11-12 giây lại quay ra thổi ngạt 2 lần trong 3-4 giây. Nếu có hai cấp cứu viên thì cứ ép tim 5 lần lại để người kia thổi ngạt 1 lần.",
            "d": "Sau khi cấp cứu thành công, để nạn nhân ở tư thế thoải mái, kê đầu vai cao hơn một chút cho dễ thở.",
            "e": "Nếu nạn nhân bị các chấn thương khác kèm theo thì ưu tiên xử lý vết thương trước."
          },
          "dap_an_dung": "e",
          "speech_id_question": "CSPL_TN_4.wav",
          "speech_id_options_A": "CSPL_TN_4_A.wav",
          "speech_id_options_B": "CSPL_TN_4_B.wav",
          "speech_id_options_C": "CSPL_TN_4_C.wav",
          "speech_id_options_D": "CSPL_TN_4_D.wav",
          "speech_id_options_E": "CSPL_TN_4_E.wav",
          "speech_id_answer": "CSPL_TN_4_ans.wav",
          "bg_image": "images\\bg\\bg4.jpg"
        },
        {
          "cau_hoi_so": 5,
          "id": "CSPL_TN_5",
          "category": "Chính sách pháp luật và Y tế",
          "subcategory": "Chính sách pháp luật về ATVSLĐ",
          "type_question": "Trắc nghiệm",
          "image_id": "images/illustrative_cspl_tn_5.jpg",
          "use_image": "Yes",
          "position_image": "Right",
          "question_image": "No",
          "cau_hoi": "Anh/Chị hãy đánh dấu câu sai trong nội dung cấp cứu người ngộ độc thực phẩm?",
          "phuong_an": {
            "a": "Người ngộ độc thực phẩm thường có biểu hiện mệt mỏi, khó chịu, có thể đau bụng, buồn nôn, tiêu chảy sau khi ăn vài giờ.",
            "b": "Cho bệnh nhân uống nước gừng nóng.",
            "c": "Cho bệnh nhân uống thuốc đau bụng mua ở hiệu thuốc.",
            "d": "Không để bệnh nhân ăn gì cho tới khi sức khỏe ổn định trở lại. Nếu tình trạng nặng thì phải gửi tới bệnh viện."
          },
          "dap_an_dung": ["b", "c"],
          "speech_id_question": "CSPL_TN_5.wav",
          "speech_id_options_A": "CSPL_TN_5_A.wav",
          "speech_id_options_B": "CSPL_TN_5_B.wav",
          "speech_id_options_C": "CSPL_TN_5_C.wav",
          "speech_id_options_D": "CSPL_TN_5_D.wav",
          "speech_id_answer": "CSPL_TN_5_ans.wav",
          "bg_image": "images\\bg\\bg5.png"
        },
        {
          "cau_hoi_so": 6,
          "id": "YT_SC_TN_1",
          "category": "Chính sách pháp luật và Y tế",
          "subcategory": "Y tế - Sơ cấp cứu",
          "type_question": "Trắc nghiệm",
          "image_id": null,
          "use_image": "No",
          "position_image": "Right",
          "question_image": "No",
          "cau_hoi": "Anh (chị) đánh dấu nội dung không chính xác trong kỹ thuật thực hành đặt garô trường hợp cụt hoặc đứt động mạch 1/3 giữa cẳng tay?",
          "phuong_an": {
            "a": "Ấn động mạch cánh tay cầm máu tạm thời.",
            "b": "Quấn mảnh gạc vòng quanh nơi định đặt garô, trên vết thương 2-3cm. Quấn garô lên mảnh gạc đủ 4 vòng.",
            "c": "Xử lý vết thương.",
            "d": "Ghi phiếu garô và cài vào ngực nạn nhân: Tên, tuổi nạn nhân, giờ đặt garo, vị trí vết thương, nơi sảy ra tai nạn, tên chức vụ người đặt ga ro.",
            "e": "Nhanh chóng chuyển nạn nhân tới cơ sở y tế đủ điều kiện xử lý vết thương.",
            "g": "Chú ý đặt ga rô không để lấu quá 6 giờ, nới garô trên đường vận chuyển 20-30ph một lần, ít nhất 1 lần một giờ, mỗi lần 1-2 phút."
          },
          "dap_an_dung": "b",
          "speech_id_question": "YT_SC_TN_1.wav",
          "speech_id_options_A": "YT_SC_TN_1_A.wav",
          "speech_id_options_B": "YT_SC_TN_1_B.wav",
          "speech_id_options_C": "YT_SC_TN_1_C.wav",
          "speech_id_options_D": "YT_SC_TN_1_D.wav",
          "speech_id_options_E": "YT_SC_TN_1_E.wav",
          "speech_id_options_G": "YT_SC_TN_1_G.wav",
          "speech_id_answer": "YT_SC_TN_1_ans.wav",
          "bg_image": "images\\bg\\bg6.png"
        },
        {
          "cau_hoi_so": 7,
          "id": "YT_SC_TN_2",
          "category": "Chính sách pháp luật và Y tế",
          "subcategory": "Y tế - Sơ cấp cứu",
          "type_question": "Trắc nghiệm",
          "image_id": null,
          "use_image": "No",
          "position_image": "Right",
          "question_image": "No",
          "cau_hoi": "Anh (chị) đánh dấu nội dung không chính xác trong kỹ thuật thực hành cố định gẫy xương cẳng tay tay hở?",
          "phuong_an": {
            "a": "Xử lý vết thương: - Rửa và sát khuẩn vết thương. Thấm khô. - Đặt gạc vô khuẩn che kín vết thương. - Băng vết thương. + Có vòng cố định ban đầu và kết thúc. + Rõ kiểu băng và dấu nhân, vòng băng sau đè 2/3 chiều rộng vòng băng trước",
            "b": "Đặt nẹp: Đặt hai nẹp ở mặt trước và sau cẳng tay, từ khuỷu tới khớp 3 ngón",
            "c": "Đặt đệm lót.",
            "d": "Buộc dây cố định nẹp: - Buộc trên và dưới ổ gãy. - Cố định cổ tay - bàn tay kiểu băng vòng xoắn. - Cố định khớp khuỷu kiểu băng số 8. - Treo tay tư thế cơ năng."
          },
          "dap_an_dung": "d",
          "speech_id_question": "YT_SC_TN_2.wav",
          "speech_id_options_A": "YT_SC_TN_2_A.wav",
          "speech_id_options_B": "YT_SC_TN_2_B.wav",
          "speech_id_options_C": "YT_SC_TN_2_C.wav",
          "speech_id_options_D": "YT_SC_TN_2_D.wav",
          "speech_id_answer": "YT_SC_TN_2_ans.wav",
          "bg_image": "images\\bg\\bg1.jpg"
        },
        {
          "cau_hoi_so": 8,
          "id": "YT_SC_TN_3",
          "category": "Chính sách pháp luật và Y tế",
          "subcategory": "Y tế - Sơ cấp cứu",
          "type_question": "Trắc nghiệm",
          "image_id": "images/illustrative_yt_sc_tn_3.jpg",
          "use_image": "Yes",
          "position_image": "Right",
          "question_image": "No",
          "cau_hoi": "Anh (chị) đánh dấu câu sai trong nội dung cấp cứu say nắng, say nóng dưới đây?",
          "phuong_an": {
            "a": "Đưa nạn nhân vào nơi thoáng mát, uống nước mát, chườm mát, quạt mát để dần hồi phục.",
            "b": "Nếu tình trạng nặng hoặc không cải thiện sau khi sơ cứu thì chuyển nhanh đến bệnh viện.",
            "c": "Chườm đá lạnh hoặc cho nạn nhân uống thuốc hạ sốt để chóng hạ nhiệt."
          },
          "dap_an_dung": "c",
          "speech_id_question": "YT_SC_TN_3.wav",
          "speech_id_options_A": "YT_SC_TN_3_A.wav",
          "speech_id_options_B": "YT_SC_TN_3_B.wav",
          "speech_id_options_C": "YT_SC_TN_3_C.wav",
          "speech_id_options_D": null,
          "speech_id_answer": "YT_SC_TN_3_ans.wav",
          "bg_image": "images\\bg\\bg1.jpg"
        }
      ]
    },
    "phong_chay_chua_chay": {
      "trac_nghiem": [
        {
          "cau_hoi_so": 1,
          "id": "PCCC_TN_1",
          "category": "Phòng cháy chữa cháy",
          "subcategory": "Lĩnh vực PCCC",
          "type_question": "Trắc nghiệm",
          "image_id": "images/illustrative_pccc_tn_1.jpg",
          "use_image": "Yes",
          "position_image": "Right",
          "question_image": "No",
          "cau_hoi": "Anh/Chị hãy cho biết những yếu tố nào sau đây cần thiết cho sự cháy?",
          "phuong_an": {
            "a": "Chất cháy, ô xy.",
            "b": "Ô xy, nguồn nhiệt.",
            "c": "Nguồn nhiệt.",
            "d": "Chất cháy, ô xy, nguồn nhiệt."
          },
          "dap_an_dung": "d",
          "speech_id_question": "PCCC_TN_1.wav",
          "speech_id_options_A": "PCCC_TN_1_A.wav",
          "speech_id_options_B": "PCCC_TN_1_B.wav",
          "speech_id_options_C": "PCCC_TN_1_C.wav",
          "speech_id_options_D": "PCCC_TN_1_D.wav",
          "speech_id_answer": "PCCC_TN_1_ans.wav",
          "bg_image": "images\\bg\\bg1.jpg"
        },
        {
          "cau_hoi_so": 2,
          "id": "PCCC_TN_2",
          "category": "Phòng cháy chữa cháy",
          "subcategory": "Lĩnh vực PCCC",
          "type_question": "Trắc nghiệm",
          "image_id": null,
          "use_image": "No",
          "position_image": "Right",
          "question_image": "No",
          "cau_hoi": "Anh/Chị hãy cho biết để hình thành sự cháy cần phải có những điều kiện nào?",
          "phuong_an": {
            "a": "Chất cháy, chất oxy hóa và nguồn nhiệt phải trực tiếp tiếp xúc với nhau; thời gian tiếp xúc phải đủ lớn; năng lượng của nguồn nhiệt phải đủ lớn (nhiệt độ của nguồn nhiệt bằng nhiệt độ tự bốc cháy của chất cháy); nồng độ chất cháy và chất oxy hóa phải nằm trong giới hạn nồng độ bốc cháy.",
            "b": "Chất cháy, chất oxy hóa và nguồn nhiệt phải trực tiếp tiếp xúc với nhau; thời gian tiếp xúc phải đủ lớn; nồng độ chất cháy và chất oxy hóa phải nằm trong giới hạn nồng độ bốc cháy.",
            "c": "Chất cháy, chất oxy hóa và nguồn nhiệt phải trực tiếp tiếp xúc với nhau; năng lượng của nguồn nhiệt phải đủ lớn (nhiệt độ của nguồn nhiệt bằng nhiệt độ tự bốc cháy của chất cháy); nồng độ chất cháy và chất oxy hóa phải nằm trong giới hạn nồng độ bốc cháy."
          },
          "dap_an_dung": "a",
          "speech_id_question": "PCCC_TN_2.wav",
          "speech_id_options_A": "PCCC_TN_2_A.wav",
          "speech_id_options_B": "PCCC_TN_2_B.wav",
          "speech_id_options_C": "PCCC_TN_2_C.wav",
          "speech_id_options_D": null,
          "speech_id_answer": "PCCC_TN_2_ans.wav",
          "bg_image": "images\\bg\\bg1.jpg"
        },
        {
          "cau_hoi_so": 3,
          "id": "PCCC_TN_3",
          "category": "Phòng cháy chữa cháy",
          "subcategory": "Lĩnh vực PCCC",
          "type_question": "Trắc nghiệm",
          "image_id": "images/illustrative_pccc_tn_3.jpg",
          "use_image": "Yes",
          "position_image": "Right",
          "question_image": "No",
          "cau_hoi": "Anh/Chị hãy cho biết các biện pháp cơ bản trong phòng cháy?",
          "phuong_an": {
            "a": "Quản lý chặt chẽ và sử dụng an toàn các chất cháy, chất nổ, nguồn lửa, nguồn nhiệt, thiết bị và dụng cụ sinh lửa, sinh nhiệt, chất sinh lửa, sinh nhiệt; bảo đảm các điều kiện an toàn về phòng cháy.",
            "b": "Thường xuyên, định kỳ kiểm tra phát hiện các sơ hở, thiếu sót về phòng cháy và có biện pháp khắc phục kịp thời.",
            "c": "Cả hai đáp án trên."
          },
          "dap_an_dung": "c",
          "speech_id_question": "PCCC_TN_3.wav",
          "speech_id_options_A": "PCCC_TN_3_A.wav",
          "speech_id_options_B": "PCCC_TN_3_B.wav",
          "speech_id_options_C": "PCCC_TN_3_C.wav",
          "speech_id_options_D": null,
          "speech_id_answer": "PCCC_TN_3_ans.wav",
          "bg_image": "images\\bg\\bg1.jpg"
        },
        {
          "cau_hoi_so": 4,
          "id": "PCCC_TN_4",
          "category": "Phòng cháy chữa cháy",
          "subcategory": "Lĩnh vực PCCC",
          "type_question": "Trắc nghiệm",
          "image_id": "images/illustrative_pccc_tn_4.jpg",
          "use_image": "Yes",
          "position_image": "Right",
          "question_image": "No",
          "cau_hoi": "Anh/Chị hãy cho biết các biện pháp cơ bản trong chữa cháy?",
          "phuong_an": {
            "a": "Huy động nhanh nhất các lực lượng, phương tiện để dập tắt ngay đám cháy.",
            "b": "Tập trung cứu người, cứu tài sản và chống cháy lan.",
            "c": "Thống nhất chỉ huy, điều hành trong chữa cháy.",
            "d": "Cả ba đáp án trên."
          },
          "dap_an_dung": "d",
          "speech_id_question": "PCCC_TN_4.wav",
          "speech_id_options_A": "PCCC_TN_4_A.wav",
          "speech_id_options_B": "PCCC_TN_4_B.wav",
          "speech_id_options_C": "PCCC_TN_4_C.wav",
          "speech_id_options_D": "PCCC_TN_4_D.wav",
          "speech_id_answer": "PCCC_TN_4_ans.wav",
          "bg_image": "images\\bg\\bg1.jpg"
        },
        {
          "cau_hoi_so": 5,
          "id": "PCCC_TN_5",
          "category": "Phòng cháy chữa cháy",
          "subcategory": "Lĩnh vực PCCC",
          "type_question": "Trắc nghiệm",
          "image_id": null,
          "use_image": "No",
          "position_image": "Right",
          "question_image": "No",
          "cau_hoi": "Anh/Chị cần làm gì khi phát hiện có đám cháy gần nơi làm việc?",
          "phuong_an": {
            "a": "Bình tĩnh báo động cho mọi người cùng biết; nhanh chóng báo cáo cho lãnh đạo trực tiếp; cắt điện khu vực xảy ra cháy; chủ động sử dụng mọi phương tiện chữa cháy tại chỗ để chữa cháy, cứu người; điện báo ngay cho lực lượng Cảnh sát PCCC (nếu thấy đám cháy lớn, phát triển nhanh mà lực lượng tại chỗ không thể dập tắt được) theo số máy 114; tích cực tham gia bảo vệ tài sản, chống cháy lan.",
            "b": "Bình tĩnh báo động cho mọi người cùng biết; nhanh chóng báo cáo cho lãnh đạo trực tiếp; chủ động sử dụng mọi phương tiện chữa cháy tại chỗ để chữa cháy, cứu người; điện báo ngay cho lực lượng Cảnh sát PCCC (nếu thấy đám cháy lớn, phát triển nhanh mà lực lượng tại chỗ không thể dập tắt được) theo số máy 114; tích cực tham gia bảo vệ tài sản, chống cháy lan."
          },
          "dap_an_dung": "a",
          "speech_id_question": "PCCC_TN_5.wav",
          "speech_id_options_A": "PCCC_TN_5_A.wav",
          "speech_id_options_B": "PCCC_TN_5_B.wav",
          "speech_id_options_C": null,
          "speech_id_options_D": null,
          "speech_id_answer": "PCCC_TN_5_ans.wav",
          "bg_image": "images\\bg\\bg1.jpg"
        },
        {
          "cau_hoi_so": 6,
          "id": "PCCC_TN_6",
          "category": "Phòng cháy chữa cháy",
          "subcategory": "Lĩnh vực PCCC",
          "type_question": "Trắc nghiệm",
          "image_id": null,
          "use_image": "No",
          "position_image": "Right",
          "question_image": "No",
          "cau_hoi": "Anh/Chị hãy cho biết trách nhiệm của cá nhân trong công tác PCCC?",
          "phuong_an": {
            "a": "Chấp hành quy định, nội quy, yêu cầu về PCCC của người hoặc cơ quan có thẩm quyền.",
            "b": "Tuân thủ pháp luật và nắm vững kiến thức cần thiết về PCCC; biết sử dụng dụng cụ, phương tiện PCCC thông dụng.",
            "c": "Bảo đảm an toàn về PCCC trong quá trình sử dụng nguồn lửa, nguồn nhiệt, thiết bị, dụng cụ sinh lửa, sinh nhiệt và trong bảo quản, sử dụng chất cháy; ngăn chặn nguy cơ trực tiếp phát sinh cháy, hành vi vi phạm quy định an toàn về PCCC.",
            "d": "Cả 03 đáp án trên."
          },
          "dap_an_dung": "d",
          "speech_id_question": "PCCC_TN_6.wav",
          "speech_id_options_A": "PCCC_TN_6_A.wav",
          "speech_id_options_B": "PCCC_TN_6_B.wav",
          "speech_id_options_C": "PCCC_TN_6_C.wav",
          "speech_id_options_D": "PCCC_TN_6_D.wav",
          "speech_id_answer": "PCCC_TN_6_ans.wav",
          "bg_image": "images\\bg\\bg1.jpg"
        },
        {
          "cau_hoi_so": 7,
          "id": "PCCC_TN_7",
          "category": "Phòng cháy chữa cháy",
          "subcategory": "Lĩnh vực PCCC",
          "type_question": "Trắc nghiệm",
          "image_id": null,
          "use_image": "No",
          "position_image": "Right",
          "question_image": "No",
          "cau_hoi": "Anh/Chị hãy cho biết nguyên tắc cơ bản trong hoạt động CNCH?",
          "phuong_an": {
            "a": "Ưu tiên cứu người bị nạn; thực hiện ngay các biện pháp bảo đảm an toàn tính mạng, sức khỏe, phương tiện, tài sản của người bị nạn và lực lượng CNCH.",
            "b": "Bảo đảm nhanh chóng, kịp thời, hiệu quả và thống nhất trong chỉ huy, điều hành hoạt động CNCH.",
            "c": "Lấy lực lượng, phương tiện tại chỗ là chủ yếu, lực lượng chuyên trách làm nòng cốt, huy động tổng hợp các lực lượng và nhân dân tham gia CNCH.",
            "d": "Cả 03 đáp án trên."
          },
          "dap_an_dung": "d",
          "speech_id_question": "PCCC_TN_7.wav",
          "speech_id_options_A": "PCCC_TN_7_A.wav",
          "speech_id_options_B": "PCCC_TN_7_B.wav",
          "speech_id_options_C": "PCCC_TN_7_C.wav",
          "speech_id_options_D": "PCCC_TN_7_D.wav",
          "speech_id_answer": "PCCC_TN_7_ans.wav",
          "bg_image": "images\\bg\\bg1.jpg"
        }
      ]
    }
  }
}
